[
    {
        "transactionName": "Получение заглавной страницы",
        "rawStartTime": 1605624605980,
        "rawEndTime": 1605624606452
    },
    {
        "transactionName": "Ввод логина",
        "rawStartTime": 1605624606484,
        "rawEndTime": 1605624606708
    },
    {
        "transactionName": "Кнопка поиска рейса",
        "rawStartTime": 1605624606724,
        "rawEndTime": 1605624607002
    },
    {
        "transactionName": "Ввод параметров поиска",
        "rawStartTime": 1605624607034,
        "rawEndTime": 1605624607178
    },
    {
        "transactionName": "Выбор рейса",
        "rawStartTime": 1605624607193,
        "rawEndTime": 1605624607348
    },
    {
        "transactionName": "Выход из системы",
        "rawStartTime": 1605624607380,
        "rawEndTime": 1605624607554
    }
]